{"id":16181,"name":"DvsnCheckoutRule","code":"dvsn903933374563","lastChange":{"date":"2023-07-25 08:00:06.000000","timezone_type":3,"timezone":"Europe/Berlin"},"support":true,"supportOnlyCommercial":false,"iconPath":"https://sbp-plugin-images.s3.eu-west-1.amazonaws.com/phpDVUbG5","examplePageUrl":"","moduleKey":"DvsnCheckoutRule","creationDate":{"date":"2022-11-09 13:47:00.000000","timezone_type":3,"timezone":"Europe/Berlin"},"automaticBugfixVersionCompatibility":true,"hiddenInStore":false,"releaseDate":{"date":"2022-11-10 11:37:15.000000","timezone_type":3,"timezone":"Europe/Berlin"},"plannedReleaseDate":null,"migrationSupport":false,"lastBusinessModelChangeDate":{"date":"2022-11-09 14:20:56.000000","timezone_type":3,"timezone":"Europe/Berlin"},"pluginTestingInstanceDisabled":false,"producer":{"id":1812,"prefix":"dvsn","name":"digitvision","website":"//www.digitvision.de","fixed":true,"iconPath":"https://sbp-plugin-images.s3.eu-west-1.amazonaws.com/prod1812_dv128.jpg"},"infos":[{"id":28232,"name":"Individuelle Hinweise im Warenkorb und Checkout deaktivieren nach Bedingungen","description":"\n\n\n\n\n\n\n<h2>\n    Individuelle Hinweise im Warenkorb und Checkout deaktivieren nach Bedingungen\n\n</h2><p>\n\n\n\nMit diesem Plugin können Sie Ihren Kunden im Warenkorb verschiedene Meldungen\nanzeigen, die über mächtigen Regeln des Rule Builders gesteuert werden. Sie können\naus vier verschiedenen Formen von Meldungen (Optik und Farbe) wählen\nund jede Meldung an eine beliebige Regel knüpfen. Die Regeln können sich\ndabei an den kompletten Kontext des Kunden und des Warenkorbs (und die Produkte) beziehen.\nZudem können Sie für jede Regel den weiteren Checkout / Bestellprozess unterbinden.\n\n</p><h4>Beispiele</h4><p>\n\n\nSie haben unbegrenzte Möglichkeiten um Ihre Kunden über individuelle Meldungen\nzu informieren. Hier einige Beispiele:\n</p><ul><li>über Mindestbestellwert informieren und den Checkout sperren</li><li>über Mischwarenkörbe (Spedition + DHL) informieren und den Checkout sperren</li><li>über lange Lieferzeiten informieren</li><li>über Betriebsferien informieren</li><li>über einzelne Produkte im Warenkorb informieren</li><li>über Probleme im Versand in ausgewählte Länder informieren</li></ul><h4>Optik</h4><p>\n\n\nSie können aus vier verschiedenen Standard Shopware Meldungen wählen:\n\n</p><ul><li>grüner Erfolg</li><li>blauer Hinweis</li><li>gelbe Warnung</li><li>roter Fehler</li></ul><h4>Checkout deaktivieren</h4><p>\n\n\nFür jede Meldung können Sie individuell definieren, ob zusätzlich der weitere\nCheckout / Bestellprozess deaktiviert werden soll, wenn die Regel eintritt bzw.\ndie Meldung angezeigt wird. So können Sie ganz einfach zwischen reinen informativen\nMeldungen und kritischen Fehlern differenzieren.\n\n</p><h4>Offcanvas Warenkorb</h4><p>\n\n\nZudem können Sie definieren, ob die Meldungen ausschließlich\nim Warenkorb oder zusätzlich auch im Offcanvas Warenkorb\nangezeigt werden sollen.\n\n</p><h4>Anleitung</h4><ul><li>installieren Sie die Erweiterung</li><li>in der Administration unter \"Einstellungen\" -&gt; \"Erweiterungen\" finden Sie den neuen Menüpunkt \"Checkout Regeln\"</li></ul><br><br><h4>Allgemeine Hinweise</h4><ul><li><strong>PHP 7 und PHP 8 kompatibel</strong><br>\nDie Erweiterung ist vollständig zu PHP 7.x und PHP 8.x kompatibel\n</li><li><strong>Textbausteine</strong><br>\nDie Erweiterung verwendet Textbausteine damit alle Texte und Beschriftungen bequem im backend bzw. in der Administration in andere Sprachen übersetzt werden können\n</li><li><strong>Subshop-fähig</strong><br>\nRelevante Optionen der Konfiguration können pro Subshop bzw. pro Verkaufskanal individuell angepasst werden\n</li><li><strong>Kompatibilität</strong><br>\nDie Erweiterung ist stets zur aktuellen Shopware Version und zum Shopware Standard Theme kompatibel\n</li><li><strong>Inkompatibilität</strong><br>\nSollten Sie ein individuelles Theme und/oder Erweiterungen von Drittanbietern nutzen, dann sollten Sie die Erweiterung vor dem Kauf gründlich testen. Eine Kompatibilität kann nicht garantiert werden\n</li><li><strong>Responsive</strong><br>\nEgal ob Desktop PC oder Mobiltelefon - die Erweiterung ist vollständig responsive\n</li><li><strong>Testversion</strong><br>\ndie Erweiterung kann kostenlos und unverbindlich 30 Tage lang getestet werden (siehe kostenfreien Probe-Monat der Miet-Lizenz)\n</li><li><strong>Individuelle Änderungswünsche</strong><br>\nJedes Unternehmen ist einzigartig und bedarf individueller Lösungen, die exakt auf die eigenen Arbeitsabläufe zugeschnitten sind. Nehmen Sie unverbindlich Kontakt zu mir auf, um meine Erweiterungen entsprechend Ihren Anforderungen anzupassen, um diese maßgeschneidert in Ihre hauseigenen Prozesse perfekt zu integrieren\n</li><li><strong>Haftungsausschluss</strong><br>\nDer Hersteller dieser Erweiterung haftet nicht für Schäden insbesondere nicht für mittelbare oder unmittelbare Folgeschäden, Datenverlust, entgangene Gewinne, System- oder Produktionsausfälle, die durch die Nutzung der Erweiterung entstehen - ausgenommen Vorsatz oder grobe Fahrlässigkeit\n</li></ul><h4>Über mich</h4><ul><li><strong>15+ Jahre Erfahrung</strong><br>\nSeit über 15 Jahren im E-Commerce und seit über 5 Jahren exklusiv mit Shopware. Ihr Spezialist mit umfangreichem Branchen- und Fachwissen.\n</li><li><strong>Zuverlässig</strong><br>\nShopware ist meine Leidenschaft und mein Hobby. Ich kümmere mich zuverlässig und engagiert um Ihr Projekt, als wäre es mein eigenes.\n</li><li><strong>Qualität</strong><br>\nHohe Service-Qualität steht im Mittelpunkt. Ich verwende modernste Design Patterns, aktuelle Technologien und innovative Werkzeuge.\n</li></ul><h4>Ihr kompetenter Partner</h4><p>\nBereits seit über 15 Jahren bin ich als leidenschaftlicher Web-Entwickler im E-Commerce tätig. In dieser Zeit konnte\nich bereits viele Unternehmen bei interessanten Projekten beraten und ausführend unterstützen. Dabei stehe ich für\nunkomplizierte Kommunikation, zukünftsfähige Lösungen, moderne Technologien und ein hohes Engagement.\n</p><p>\nJedes Unternehmen ist einzigartig und bedarf individueller Lösungen, die exakt auf die eigenen Arbeitsabläufe\nzugeschnitten sind. Nehmen Sie unverbindlich Kontakt zu mir auf, um meine Erweiterungen entsprechend Ihren Anforderungen\nanzupassen, um diese maßgeschneidert in Ihre hauseigenen Prozesse perfekt zu integrieren. Gerne erstelle ich Ihnen\nAngebote für Anpassungen oder ggf. individuell programmierte Erweiterungen ganz nach Ihren Wünschen.\n</p>","installationManual":"\n\n<h4>Anleitung</h4><ul><li>installieren Sie die Erweiterung</li><li>in der Administration unter \"Einstellungen\" -> \"Erweiterungen\" finden Sie den neuen Menüpunkt \"Checkout Regeln\"</li></ul>\n\n","shortDescription":"Zeigen Sie Hinweise im Warenkorb nach Bedingungen des Rule Builders an und/oder deaktivieren Sie zusätzlich den Checkout wenn definierte Regeln nicht zutreffen","highlights":"","features":""},{"id":28233,"name":"Individual notes in cart and disable checkout according to conditions","description":"\n\n\n\n\n\n\n\n<h2>\n    Disable individual notes in shopping cart and checkout according to conditions\n\n</h2><p>\n\n\n\nWith this plugin you can display various messages to your customers in the shopping cart, controlled by powerful rules of the Rule Builder. You can choose from four different forms of messages (appearance and color) and link each message to any rule. The rules can be related to the complete context of the customer and the shopping cart (and the products). In addition, for each rule you can prevent further checkout / order process.\n\n</p><h4>Examples</h4><p>\n\n\nYou have unlimited possibilities to inform your customers about individual messages. Here are some examples:\n</p><ul><li>inform about minimum order value and block checkout</li><li>inform about mixed baskets (forwarding + DHL) and lock the checkout</li><li>inform about long delivery times</li><li>inform about company vacations</li><li>inform about individual products in the shopping cart</li><li>Inform about problems in shipping to selected countries</li></ul><h4>Optics</h4><p>\n\n\nYou can choose from four different standard Shopware messages:\n\n</p><ul><li>green success</li><li>blue note</li><li>yellow warning</li><li>red error</li></ul><h4>Disable checkout</h4><p>\n\n\nFor each message, you can individually define whether the further checkout / order process should also be disabled when the rule occurs or the message is displayed. This way you can easily differentiate between purely informative messages and critical errors.\n\n</p><h4>Offcanvas cart</h4><p>\n\n\nIn addition, you can define whether the messages should be displayed exclusively in the shopping cart or additionally also in the offcanvas shopping cart.\n\n</p><h4>Instructions</h4><ul><li>install the extension</li><li>in the administration under \"Settings\" -> \"Extensions\" you will find the new menu item \"Checkout rules\"</li></ul><br /><br /><h4>General information</h4><ul><li><strong>PHP 7 and PHP 8 compatible</strong><br />\nThe plugin is fully compatible with PHP 7.x and PHP 8.x\n</li><li><strong>Snippets</strong><br />\nThe plugin uses snippets so that all texts and labels can be translated into other languages in the backend / in the administration\n</li><li><strong>Subshop-able</strong><br />\nRelevant configuration options can be individually adapted for each subshop / sales channel\n</li><li><strong>Compatibility</strong><br />\nThe plugin is always compatible with the latest Shopware version and the Shopware standard theme\n</li><li><strong>Incompatibility</strong><br />\nIf you are using a custom theme and/or third-party plugins, you should test the plugin thoroughly before buying. A compatibility can not be guaranteed\n</li><li><strong>Responsive</strong><br />\nWhether desktop PC or mobile phone - the plugin is fully responsive\n</li><li><strong>Test version</strong><br />\nThe plugin can be tested free of charge and without obligation for 30 days (see free trial month of the rental license)\n</li><li><strong>Individual change requests</strong><br />\nEvery company is unique and requires individual solutions that are precisely tailored to its own workflows. Please contact me without obligation to adapt my plugins according to your requirements in order to integrate them perfectly into your in-house processes\n</li><li><strong>Liability disclaimer</strong><br />\nThe plugin manufacturer is not liable for damages, in particular not for direct or indirect consequential damages, data loss, lost profits, system or production failures that result from the use of the plugin - except for intent or gross negligence\n</li></ul><h4>About me</h4><ul><li><strong>15+ years of experience</strong><br />\nFor over 15 years in e-commerce and for over 5 years exclusively with shopware. Your specialist with extensive industry and technical knowledge.\n</li><li><strong>Reliable</strong><br />\nShopware is my passion and my hobby. I take care of your project in a reliable and committed way as if it were my own.\n</li><li><strong>Quality</strong><br />\nHigh service quality is the focus. I use state-of-the-art design patterns, current technologies and innovative tools.\n</li></ul><h4>Your competent partner</h4><p>\nFor more than 15 years I have been working as a passionate web developer in e-commerce. In this time\nI have already advised and supported many companies in interesting projects. Thereby I stand for\nuncomplicated communication, future-proof solutions, modern technologies and a high level of commitment.\n</p><p>\nEvery company is unique and requires individual solutions that are precisely tailored to its own workflows.\nGet in contact with me without obligation, to get my plugins according to your requirements\nin order to integrate them perfectly into your in-house processes. I would be happy to provide you with\noffers for adaptations or, if necessary, individually programmed plugins according to your wishes.\n</p>","installationManual":"\n\n<h4>Instructions</h4><ul><li>install the extension</li><li>in the administration under \"Settings\" -> \"Extensions\" you will find the new menu item \"Checkout rules\"</li></ul>\n\n","shortDescription":"Show hints in the shopping cart according to rule builder conditions and/or additionally disable the complete checkout if defined rules from the rule builder do not apply","highlights":"","features":""}],"addons":[],"standardLocale":{"id":1,"name":"de_DE"},"priceModels":[{"id":166728,"bookingKey":"dvsn903933374563","bookingText":"Individual notes in cart and disable checkout according to conditions","price":134.1,"subscription":true,"discount":10,"discr":"priceModelBuy"},{"id":166727,"bookingKey":"dvsn903933374563_M","bookingText":"Individual notes in cart and disable checkout according to conditions","price":29,"duration":1,"trialPhaseIncluded":true,"discount":0,"discountAppliesForMonths":null,"discr":"priceModelRent"}],"pictures":[{"remoteLink":"https://sbp-plugin-images.s3.eu-west-1.amazonaws.com/phpdHgXrO","preview":true,"priority":9900,"id":101588},{"remoteLink":"https://sbp-plugin-images.s3.eu-west-1.amazonaws.com/phpjjZDtP","preview":false,"priority":9800,"id":101590},{"remoteLink":"https://sbp-plugin-images.s3.eu-west-1.amazonaws.com/phpJxCgyN","preview":false,"priority":9700,"id":101591},{"remoteLink":"https://sbp-plugin-images.s3.eu-west-1.amazonaws.com/phpYgDtbG","preview":false,"priority":9600,"id":101592},{"remoteLink":"https://sbp-plugin-images.s3.eu-west-1.amazonaws.com/phpGWYp8J","preview":false,"priority":9500,"id":101593},{"remoteLink":"https://sbp-plugin-images.s3.eu-west-1.amazonaws.com/phpVaaq4Z","preview":false,"priority":9400,"id":101594},{"remoteLink":"https://sbp-plugin-images.s3.eu-west-1.amazonaws.com/php1fP0J0","preview":false,"priority":8900,"id":101595},{"remoteLink":"https://sbp-plugin-images.s3.eu-west-1.amazonaws.com/phpDqPh6H","preview":false,"priority":4900,"id":101596},{"remoteLink":"https://sbp-plugin-images.s3.eu-west-1.amazonaws.com/phpP3anbU","preview":false,"priority":4800,"id":101597},{"remoteLink":"https://sbp-plugin-images.s3.eu-west-1.amazonaws.com/php2obA8y","preview":false,"priority":4700,"id":101598},{"remoteLink":"https://sbp-plugin-images.s3.eu-west-1.amazonaws.com/phpAATnmI","preview":false,"priority":4600,"id":101599},{"remoteLink":"https://sbp-plugin-images.s3.eu-west-1.amazonaws.com/phpFy9Fh6","preview":false,"priority":2900,"id":101600}],"comments":[],"ratingAverage":0,"label":"Individuelle Hinweise im Warenkorb und Checkout deaktivieren nach Bedingungen","description":"<h2>\n    Individuelle Hinweise im Warenkorb und Checkout deaktivieren nach Bedingungen\n\n</h2><p>\n\n\n\nMit diesem Plugin können Sie Ihren Kunden im Warenkorb verschiedene Meldungen\nanzeigen, die über mächtigen Regeln des Rule Builders gesteuert werden. Sie können\naus vier verschiedenen Formen von Meldungen (Optik und Farbe) wählen\nund jede Meldung an eine beliebige Regel knüpfen. Die Regeln können sich\ndabei an den kompletten Kontext des Kunden und des Warenkorbs (und die Produkte) beziehen.\nZudem können Sie für jede Regel den weiteren Checkout / Bestellprozess unterbinden.\n\n</p><h4>Beispiele</h4><p>\n\n\nSie haben unbegrenzte Möglichkeiten um Ihre Kunden über individuelle Meldungen\nzu informieren. Hier einige Beispiele:\n</p><ul><li>über Mindestbestellwert informieren und den Checkout sperren</li><li>über Mischwarenkörbe (Spedition + DHL) informieren und den Checkout sperren</li><li>über lange Lieferzeiten informieren</li><li>über Betriebsferien informieren</li><li>über einzelne Produkte im Warenkorb informieren</li><li>über Probleme im Versand in ausgewählte Länder informieren</li></ul><h4>Optik</h4><p>\n\n\nSie können aus vier verschiedenen Standard Shopware Meldungen wählen:\n\n</p><ul><li>grüner Erfolg</li><li>blauer Hinweis</li><li>gelbe Warnung</li><li>roter Fehler</li></ul><h4>Checkout deaktivieren</h4><p>\n\n\nFür jede Meldung können Sie individuell definieren, ob zusätzlich der weitere\nCheckout / Bestellprozess deaktiviert werden soll, wenn die Regel eintritt bzw.\ndie Meldung angezeigt wird. So können Sie ganz einfach zwischen reinen informativen\nMeldungen und kritischen Fehlern differenzieren.\n\n</p><h4>Offcanvas Warenkorb</h4><p>\n\n\nZudem können Sie definieren, ob die Meldungen ausschließlich\nim Warenkorb oder zusätzlich auch im Offcanvas Warenkorb\nangezeigt werden sollen.\n\n</p><h4>Anleitung</h4><ul><li>installieren Sie die Erweiterung</li><li>in der Administration unter \"Einstellungen\" -&gt; \"Erweiterungen\" finden Sie den neuen Menüpunkt \"Checkout Regeln\"</li></ul><br /><br /><h4>Allgemeine Hinweise</h4><ul><li><strong>PHP 7 und PHP 8 kompatibel</strong><br />\nDie Erweiterung ist vollständig zu PHP 7.x und PHP 8.x kompatibel\n</li><li><strong>Textbausteine</strong><br />\nDie Erweiterung verwendet Textbausteine damit alle Texte und Beschriftungen bequem im backend bzw. in der Administration in andere Sprachen übersetzt werden können\n</li><li><strong>Subshop-fähig</strong><br />\nRelevante Optionen der Konfiguration können pro Subshop bzw. pro Verkaufskanal individuell angepasst werden\n</li><li><strong>Kompatibilität</strong><br />\nDie Erweiterung ist stets zur aktuellen Shopware Version und zum Shopware Standard Theme kompatibel\n</li><li><strong>Inkompatibilität</strong><br />\nSollten Sie ein individuelles Theme und/oder Erweiterungen von Drittanbietern nutzen, dann sollten Sie die Erweiterung vor dem Kauf gründlich testen. Eine Kompatibilität kann nicht garantiert werden\n</li><li><strong>Responsive</strong><br />\nEgal ob Desktop PC oder Mobiltelefon - die Erweiterung ist vollständig responsive\n</li><li><strong>Testversion</strong><br />\ndie Erweiterung kann kostenlos und unverbindlich 30 Tage lang getestet werden (siehe kostenfreien Probe-Monat der Miet-Lizenz)\n</li><li><strong>Individuelle Änderungswünsche</strong><br />\nJedes Unternehmen ist einzigartig und bedarf individueller Lösungen, die exakt auf die eigenen Arbeitsabläufe zugeschnitten sind. Nehmen Sie unverbindlich Kontakt zu mir auf, um meine Erweiterungen entsprechend Ihren Anforderungen anzupassen, um diese maßgeschneidert in Ihre hauseigenen Prozesse perfekt zu integrieren\n</li><li><strong>Haftungsausschluss</strong><br />\nDer Hersteller dieser Erweiterung haftet nicht für Schäden insbesondere nicht für mittelbare oder unmittelbare Folgeschäden, Datenverlust, entgangene Gewinne, System- oder Produktionsausfälle, die durch die Nutzung der Erweiterung entstehen - ausgenommen Vorsatz oder grobe Fahrlässigkeit\n</li></ul><h4>Über mich</h4><ul><li><strong>15+ Jahre Erfahrung</strong><br />\nSeit über 15 Jahren im E-Commerce und seit über 5 Jahren exklusiv mit Shopware. Ihr Spezialist mit umfangreichem Branchen- und Fachwissen.\n</li><li><strong>Zuverlässig</strong><br />\nShopware ist meine Leidenschaft und mein Hobby. Ich kümmere mich zuverlässig und engagiert um Ihr Projekt, als wäre es mein eigenes.\n</li><li><strong>Qualität</strong><br />\nHohe Service-Qualität steht im Mittelpunkt. Ich verwende modernste Design Patterns, aktuelle Technologien und innovative Werkzeuge.\n</li></ul><h4>Ihr kompetenter Partner</h4><p>\nBereits seit über 15 Jahren bin ich als leidenschaftlicher Web-Entwickler im E-Commerce tätig. In dieser Zeit konnte\nich bereits viele Unternehmen bei interessanten Projekten beraten und ausführend unterstützen. Dabei stehe ich für\nunkomplizierte Kommunikation, zukünftsfähige Lösungen, moderne Technologien und ein hohes Engagement.\n</p><p>\nJedes Unternehmen ist einzigartig und bedarf individueller Lösungen, die exakt auf die eigenen Arbeitsabläufe\nzugeschnitten sind. Nehmen Sie unverbindlich Kontakt zu mir auf, um meine Erweiterungen entsprechend Ihren Anforderungen\nanzupassen, um diese maßgeschneidert in Ihre hauseigenen Prozesse perfekt zu integrieren. Gerne erstelle ich Ihnen\nAngebote für Anpassungen oder ggf. individuell programmierte Erweiterungen ganz nach Ihren Wünschen.\n</p>","installationManual":"<h4>Anleitung</h4><ul><li>installieren Sie die Erweiterung</li><li>in der Administration unter \"Einstellungen\" -&gt; \"Erweiterungen\" finden Sie den neuen Menüpunkt \"Checkout Regeln\"</li></ul>","version":"2.0.0","changelog":[{"version":"2.0.0","text":"- added shopware 6.5 compatibility","creationDate":{"date":"2023-04-02 11:53:49.000000","timezone_type":3,"timezone":"Europe/Berlin"}},{"version":"1.0.0","text":"- first plugin version","creationDate":{"date":"2022-11-09 15:03:47.000000","timezone_type":3,"timezone":"Europe/Berlin"}}],"link":"http://store.shopware.com:80/en/search?sSearch=dvsn903933374563","redirectToStore":false,"lowestPriceValue":29}